odoo/addons/l10n_th_sequence_refactored/README.rst
odoo/addons/l10n_th_sequence_refactored/__init__.py
odoo/addons/l10n_th_sequence_refactored/__manifest__.py
odoo/addons/l10n_th_sequence_refactored/i18n/l10n_th_sequence_refactored.pot
odoo/addons/l10n_th_sequence_refactored/models/__init__.py
odoo/addons/l10n_th_sequence_refactored/models/ir_sequence.py
odoo/addons/l10n_th_sequence_refactored/models/ir_sequence_date_range.py
odoo/addons/l10n_th_sequence_refactored/readme/CONTRIBUTORS.rst
odoo/addons/l10n_th_sequence_refactored/readme/DESCRIPTION.rst
odoo/addons/l10n_th_sequence_refactored/static/description/icon.png
odoo/addons/l10n_th_sequence_refactored/static/description/index.html
odoo/addons/l10n_th_sequence_refactored/tests/__init__.py
odoo/addons/l10n_th_sequence_refactored/tests/test_ir_sequence.py
odoo/addons/l10n_th_sequence_refactored/tests/test_ir_sequence_date_range.py
odoo/addons/l10n_th_sequence_refactored/views/ir_sequence_view.xml
odoo_addon_l10n_th_sequence_refactored-15.0.1.0.0.4.dist-info/METADATA
odoo_addon_l10n_th_sequence_refactored-15.0.1.0.0.4.dist-info/WHEEL
odoo_addon_l10n_th_sequence_refactored-15.0.1.0.0.4.dist-info/top_level.txt
odoo_addon_l10n_th_sequence_refactored-15.0.1.0.0.4.dist-info/RECORD
